[{"url": "https://www.techradar.com/rss", "link": "https://www.techradar.com/news/larry-ellison-wants-to-build-an-internet-of-clouds/", "title": "Larry Ellison wants to build \u201can internet of clouds\u201d", "date_published": "2022-10-18 22:30:09+00:00", "description": "An interconnected multi-cloud approach is the future, says Oracle CTO Larry Ellison."}, {"url": "https://www.techradar.com/rss", "link": "https://www.techradar.com/news/over-2-million-mydeal-users-have-had-their-data-sold-online-after-a-breach/", "title": "Millions of MyDeal users have data sold online after breach", "date_published": "2022-10-18 22:06:06+00:00", "description": "MyDeal customer data stolen and sold for $600 on an underground forum."}, {"url": "https://www.techradar.com/rss", "link": "https://www.techradar.com/news/samsung-unveils-lpddr5x-ram-thats-likely-to-end-in-galaxy-s23-range/", "title": "Samsung unveils LPDDR5x RAM that's likely to end in Galaxy S23 range", "date_published": "2022-10-18 21:00:57+00:00", "description": "Samsung claims it has broken its own record for transfer speeds via an integration with Qualcomm's Snapdragon processors."}, {"url": "https://www.techradar.com/rss", "link": "https://www.techradar.com/news/oracle-and-nvidia-want-to-help-your-business-use-ai-better/", "title": "Oracle and Nvidia want to help your business use AI better", "date_published": "2022-10-18 20:10:55+00:00", "description": "Tens of thousands of Nvidia GPUs look to supercharge Oracle Cloud."}, {"url": "https://www.techradar.com/rss", "link": "https://www.techradar.com/news/near-undetectable-hacking-tool-up-for-sale-on-malware-forum/", "title": "'Near-undetectable' hacking tool up for sale on malware forum", "date_published": "2022-10-18 20:00:30+00:00", "description": "A fix was released for a flaw plaguing numerous versions of Windows and Windows Server."}, {"url": "https://www.techradar.com/rss", "link": "https://www.techradar.com/news/microsoft-has-announced-some-serious-employee-layoffs/", "title": "Microsoft has announced some serious employee layoffs", "date_published": "2022-10-18 19:41:15+00:00", "description": "Microsoft is the latest tech firm to make significant layoffs in 2022."}, {"url": "https://www.techradar.com/rss", "link": "https://www.techradar.com/news/google-just-revealed-a-totally-new-operating-system/", "title": "Google just revealed another totally new operating system", "date_published": "2022-10-18 18:56:25+00:00", "description": "KataOS is designed to ensure maximum security for more and more smart devices."}, {"url": "https://www.techradar.com/rss", "link": "https://www.techradar.com/news/bypass-for-windows-trusted-file-label-gets-unofficial-patch/", "title": "Bypass for Windows trusted file label gets unofficial patch", "date_published": "2022-10-18 16:47:53+00:00", "description": "Mark of the Web flaw has been resolved, but not by Microsoft."}, {"url": "https://www.techradar.com/rss", "link": "https://www.techradar.com/news/xbox-series-xs-premium-controller-is-now-in-xbox-design-lab/", "title": "Xbox Series X's premium controller is now in Xbox Design Lab", "date_published": "2022-10-18 16:33:30+00:00", "description": "Xbox Series X's Elite Series 2 controller has arrived in the custom-pad making Xbox Design Lab."}, {"url": "https://www.techradar.com/rss", "link": "https://www.techradar.com/news/huge-savings-on-privacy-save-up-to-68-with-nordvpns-black-friday-deal/", "title": "Huge savings on privacy - save up to 68% with NordVPN's Black Friday deal", "date_published": "2022-10-18 16:23:53+00:00", "description": "For its Black Friday and Cyber Monday VPN deals, NordVPN has just dropped its prices and added some tasty freebies."}, {"url": "https://www.techradar.com/rss", "link": "https://www.techradar.com/news/the-ipad-pro-2022-inches-closer-to-replacing-your-macbook/", "title": "The iPad Pro 2022 inches closer to replacing your MacBook", "date_published": "2022-10-18 16:23:36+00:00", "description": "The iPad Pro 2022 uses the Apple M2 chip, and the real benefit will be for iPad OS features"}, {"url": "https://www.techradar.com/rss", "link": "https://www.techradar.com/news/new-cheaper-apple-tv-4k-with-hdr10-launches-developing/", "title": "New cheaper Apple TV 4K with HDR10+ launches (developing)", "date_published": "2022-10-18 16:10:56+00:00", "description": "Apple's next-generation streaming box has landed, bringing with it a speedier A15 Bionic chip and HDR10+, but few other changes."}, {"url": "https://www.techradar.com/rss", "link": "https://www.techradar.com/news/zoom-for-mac-users-should-update-now-to-fix-a-massive-security-flaw/", "title": "Zoom for Mac users should update now to fix a massive security flaw", "date_published": "2022-10-18 16:03:38+00:00", "description": "Users urged to update Zoom for Mac desktop client to combat potential flaws."}, {"url": "https://www.techradar.com/rss", "link": "https://www.techradar.com/news/the-rings-of-power-season-2-everything-we-know-so-far/", "title": "The Rings of Power season 2: everything we know so far", "date_published": "2022-10-18 16:00:00+00:00", "description": "Here's everything we know about The Rings of Power season 2 on Prime Video."}, {"url": "https://www.techradar.com/rss", "link": "https://www.techradar.com/news/live/oracle-cloud-world-live-blog-day-one-as-it-happens/", "title": "Oracle Cloud World live blog: day one as it happens", "date_published": "2022-10-18 14:28:05+00:00", "description": "We're live at Oracle Cloud World with all the latest news."}, {"url": "https://www.techradar.com/rss", "link": "https://www.techradar.com/news/hermeticwiper-malware-victims-are-reporting-ransomware-attacks-too/", "title": "HermeticWiper malware victims are now reporting ransomware attacks too", "date_published": "2022-10-18 14:18:16+00:00", "description": "Microsoft is trying to determine if the attacks are linked, while the attackers themselves remain unknown."}, {"url": "https://www.techradar.com/rss", "link": "https://www.techradar.com/news/nhs-data-stolen-from-contractor-in-serious-cyberattack/", "title": "NHS data stolen from contractor in serious cyberattack", "date_published": "2022-10-18 14:01:43+00:00", "description": "Advanced confirms it suffered a data breach that leaked NHS information."}, {"url": "https://www.techradar.com/rss", "link": "https://www.techradar.com/news/nvidia-rtx-4090-gpu-is-alarmingly-good-at-cracking-passwords/", "title": "Nvidia RTX 4090 GPU is alarmingly good at cracking passwords", "date_published": "2022-10-18 13:42:39+00:00", "description": "Tech like Nvidia\u2019s new flagship graphics card could make it easier for bad guys to brute force passwords."}, {"url": "https://www.techradar.com/rss", "link": "https://www.techradar.com/news/google-workspace-really-wants-you-to-tell-your-team-where-you-are/", "title": "Google Workspace really wants you to tell your team where you are", "date_published": "2022-10-18 13:38:00+00:00", "description": "Google Workspace adds new control for IT admins in the name of hybrid working, at the expense of your privacy."}, {"url": "https://www.techradar.com/rss", "link": "https://www.techradar.com/news/live/apple-ipad-october-2022-live-blog/", "title": "Apple iPad 2022 live blog: M2 iPad Pro and a new entry-level iPad expected", "date_published": "2022-10-18 13:15:28+00:00", "description": "New iPads are coming, tune in for all you need to know about Apple's expected M2-powered tablets."}, {"url": "https://www.techradar.com/rss", "link": "https://www.techradar.com/news/new-galaxy-s23-case-leaks-reinforce-s22-ultra-inspired-design-for-whole-lineup/", "title": "New Galaxy S23 case leaks reinforce S22 Ultra-inspired design for whole lineup", "date_published": "2022-10-18 10:41:15+00:00", "description": "New case leaks double-down on S22 Ultra-inspired design influence."}, {"url": "https://www.techradar.com/rss", "link": "https://www.techradar.com/news/the-dceu-should-forget-about-its-idea-for-a-multiverse-for-now/", "title": "The DCEU should forget about its idea for a multiverse \u2013 for now", "date_published": "2022-10-18 10:35:32+00:00", "description": "The DC Extended Universe should forego an MCU-style approach in favor of smaller superhero-specific universes."}, {"url": "https://www.techradar.com/rss", "link": "https://www.techradar.com/news/dont-install-the-new-resident-evil-8-patch-if-you-value-your-save-file/", "title": "Don't install the new Resident Evil 8 patch if you value your save file", "date_published": "2022-10-18 10:22:06+00:00", "description": "A recent bug in Resident Evil 8 has caused chaos for PC users, but what caused the havoc?"}, {"url": "https://www.techradar.com/rss", "link": "https://www.techradar.com/news/look-out-amd-microsoft-is-tanking-your-cpu-performance-again-with-windows-11/", "title": "Look out, AMD \u2013 Microsoft is tanking your CPU performance again with Windows 11", "date_published": "2022-10-18 10:21:39+00:00", "description": "If you're considering getting a Ryzen 9 7950X for gaming, you might want to look at AMD\u2019s cheaper options first."}, {"url": "https://www.techradar.com/rss", "link": "https://www.techradar.com/news/netflixs-account-sharing-crackdown-gets-a-little-less-painful/", "title": "Netflix's account-sharing crackdown gets a little less painful", "date_published": "2022-10-18 10:17:58+00:00", "description": "Netflix has announced a new feature, Profile Transfer, that lets you move your user profile to a new Netflix account."}, {"url": "https://www.techradar.com/rss", "link": "https://www.techradar.com/news/nvidia-rtx-4090-gpu-power-cable-woes-solved-by-this-nifty-invention/", "title": "Nvidia RTX 4090 GPU power cable woes solved by this nifty invention", "date_published": "2022-10-18 10:03:28+00:00", "description": "Some RTX 4090 owners have a real problem with cabling, but a solution is available (not for free, though)."}, {"url": "https://www.techradar.com/rss", "link": "https://www.techradar.com/news/three-new-ipads-could-land-today-alongside-ipados-16/", "title": "Three new iPads could land today, alongside iPadOS 16", "date_published": "2022-10-18 09:07:10+00:00", "description": "It looks very likely that the iPad Pro 2022 line will land today, with a new basic iPad possibly arriving too."}, {"url": "https://www.techradar.com/rss", "link": "https://www.techradar.com/news/live/adobe-max-2022-live-all-the-latest-updates-for-photoshop-lightroom-and-more/", "title": "Adobe Max 2022 live: all the latest updates for Photoshop, Lightroom and more", "date_published": "2022-10-18 06:51:11+00:00", "description": "Join us as we pixel peep the handy tools coming to Adobe\u2019s apps"}]