[{"url": "https://feeds.feedburner.com/niebezpiecznik/", "link": "https://niebezpiecznik.pl/post/uber-zhackowany/", "title": "Uber zhackowany!", "date_published": "2022-09-16 07:23:55+00:00", "description": "<a href=\"https://niebezpiecznik.pl/post/uber-zhackowany/\"><img align=\"left\" alt=\"\" class=\"alignleft tfe wp-post-image\" height=\"100\" hspace=\"5\" src=\"https://niebezpiecznik.pl/wp-content/uploads/2022/09/uber-hacked-150x150.jpg\" width=\"100\" /></a>Kto\u015b przej\u0105\u0142 infrastruktur\u0119 Ubera. Do sieci wyciek\u0142y screeny z wewn\u0119trznych system\u00f3w firmy. Atakuj\u0105cy wypowiada\u0142 si\u0119\u00a0te\u017c\u00a0korzystaj\u0105c z oficjalnych kont sp\u00f3\u0142ki. Wci\u0105\u017c nie wiadomo, jakie dane klient\u00f3w pozyskano. W\u0142amanie do Ubera Wygl\u0105da na to, \u017ce dzi\u015b zi\u015bci"}]