[{"url": "https://wydarzenia.interia.pl/polska/feed", "link": "https://wydarzenia.interia.pl/kraj/news-tam-grzybow-jest-najwiecej-imgw-zdradza-gdzie-najlepiej-wybr,nId,6311709", "title": "Tam grzyb\u00f3w jest najwi\u0119cej. IMGW zdradza, gdzie najlepiej wybra\u0107 si\u0119 z koszykiem", "date_published": "2022-09-27 12:37:30+00:00", "description": "<p><a href=\"https://wydarzenia.interia.pl/kraj/news-tam-grzybow-jest-najwiecej-imgw-zdradza-gdzie-najlepiej-wybr,nId,6311709\"><img align=\"left\" alt=\"Tam grzyb\u00f3w jest najwi\u0119cej. IMGW zdradza, gdzie najlepiej wybra\u0107 si\u0119 z koszykiem\" src=\"https://i.iplsc.com/tam-grzybow-jest-najwiecej-imgw-zdradza-gdzie-najlepiej-wybr/000G4I5D88J1JK8J-C321.jpg\" /></a>Grzyby to has\u0142o, na kt\u00f3re wielu Polak\u00f3w reaguje wielkim entuzjazmem. Sprawdzamy, czy aura w najbli\u017csze dni b\u0119dzie sprzyja\u0107 grzybiarzom czy wr\u0119cz przec"}]