[{"age": 0, "language": "pl-PL", "dead": false, "page_rating_visits": 0, "page_rating": 0, "date_published": "2005-11-26T20:22:07+00:00", "permanent": false, "tags": ["feminism", "poland", "discrimination", "socialism", "sexism"], "comments": [], "album": null, "vote": 30.0, "source": "http://www.psychologia.net.pl", "title": "Feminizm - nowa wersja komunizmu", "description": "Feminizm - nowa wersja komunizmu", "page_rating_contents": 0, "thumbnail": null, "artist": null, "link": "http://www.psychologia.net.pl/artykul.php?level=61", "user": "rumpel", "bookmarked": true, "page_rating_votes": 0}]