[{"url": "http://rss.nytimes.com/services/xml/rss/nyt/Technology.xml", "link": "https://www.nytimes.com/2022/10/13/technology/fcc-huawei-china.html", "title": "F.C.C. Readies Vote on Banning New Huawei and ZTE Devices", "date_published": "2022-10-13 16:38:42+00:00", "description": "The vote, which is expected to pass, is required by a law that President Biden signed last year."}, {"url": "http://rss.nytimes.com/services/xml/rss/nyt/Technology.xml", "link": "https://www.nytimes.com/2022/10/13/us/politics/biden-china-technology-semiconductors.html", "title": "With New Crackdown, Biden Wages Global Campaign on Chinese Technology", "date_published": "2022-10-13 15:37:27+00:00", "description": "U.S. officials pushed to choke off China\u2019s access to critical semiconductor technology after internal debates and tough negotiations with allies."}, {"url": "http://rss.nytimes.com/services/xml/rss/nyt/Technology.xml", "link": "https://www.nytimes.com/2022/10/13/technology/gamers-malware-minecraft-roblox.html", "title": "Gaming Is Booming. That\u2019s Catnip for Cybercriminals.", "date_published": "2022-10-13 13:48:00+00:00", "description": "Cybersecurity experts warn that threats lurk in cheat codes, microtransactions and messages from fellow players."}]