[{"url": "https://tvn24.pl/wiadomosci-z-kraju,3.xml", "link": "https://tvn24.pl/biznes/z-kraju/wyniki-lotto-z-dnia-221022-liczby-z-ostatniego-losowania-6175747?source=rss", "title": "Wyniki Lotto z 22 pa\u017adziernika 2022. Jakie liczby pad\u0142y podczas ostatniego losowania?", "date_published": "2022-10-23 06:26:46+00:00", "description": "<img alt=\"Wyniki Lotto z 22 pa\u017adziernika 2022. Jakie liczby pad\u0142y podczas ostatniego losowania?\" src=\"https://tvn24.pl/biznes/najnowsze/cdn-zdjecie6df609e557328745367b126f5dd34653-lotto-16-jpg-3815826/alternates/LANDSCAPE_1280\" />\n    W sobotnim losowaniu Lotto nie pad\u0142a g\u0142\u00f3wna wygrana. Kumulacja ro\u015bnie do czterech milion\u00f3w z\u0142otych. Oto wyniki Lotto, Lotto Plus i Super Szansa z dnia 22 pa\u017adziernika 2022 roku."}]