[{"permanent": false, "tags": ["billionaires", "polititians", "bilderberg meeting", "democracy"], "language": "en", "user": "rumpel", "page_rating_visits": 0, "link": "https://www.trivia-library.com/c/most-powerful-in-the-world-the-bilderberg-group-part-2.htm", "description": "Most Powerful in the World - The Bilderberg Group Part 2", "page_rating_votes": 0, "date_published": "1975-09-07T06:59:55+00:00", "source": "https://www.trivia-library.com", "comments": [], "album": "https://www.trivia-library.com", "thumbnail": null, "dead": false, "page_rating_contents": 0, "page_rating": 0, "age": 0, "title": "Most Powerful in the World - The Bilderberg Group Part 2", "artist": "https://www.trivia-library.com", "vote": 0, "bookmarked": true}, {"permanent": false, "tags": ["democracy", "trilateral commission"], "language": "en", "user": "rumpel", "page_rating_visits": 0, "link": "https://en.wikipedia.org/wiki/The_Crisis_of_Democracy", "description": "The Crisis of Democracy - Wikipedia", "page_rating_votes": 0, "date_published": "1975-09-07T06:53:50+00:00", "source": "https://en.wikipedia.org", "comments": [], "album": "https://en.wikipedia.org", "thumbnail": null, "dead": false, "page_rating_contents": 0, "page_rating": 0, "age": 0, "title": "The Crisis of Democracy - Wikipedia", "artist": "https://en.wikipedia.org", "vote": 0, "bookmarked": true}, {"permanent": false, "tags": ["satanism", "occult"], "language": "en-US", "user": "rumpel", "page_rating_visits": 0, "link": "https://www.youtube.com/watch?v=SgK54Vc-GZ0", "description": "Christopher Lee 1975", "page_rating_votes": 0, "date_published": "1975-01-13T16:04:49+00:00", "source": "https://www.youtube.com/feeds/videos.xml?channel_id=UCjCoSWwlUJqgkcdGNQqkwjA", "comments": [], "album": null, "thumbnail": null, "dead": false, "page_rating_contents": 0, "page_rating": 0, "age": 0, "title": "Christopher Lee 1975", "artist": null, "vote": 0, "bookmarked": true}]