[{"album": "https://www.commondreams.org", "permanent": false, "artist": "https://www.commondreams.org", "page_rating_votes": 0, "title": "Opinion | To Save US Democracy, Tax the Rich at 90% | Common Dreams", "language": "en", "bookmarked": true, "page_rating_contents": 0, "user": "rumpel", "dead": false, "page_rating": 0, "date_published": "1936-09-07T10:06:11+00:00", "page_rating_visits": 0, "vote": 0, "thumbnail": null, "link": "https://www.commondreams.org/opinion/to-save-us-democracy-tax-the-rich-at-90?share_id=7681280&utm_campaign=RebelMouse&utm_content=Common+Dreams&utm_medium=social&utm_source=twitter", "age": 0, "comments": [], "source": "https://www.commondreams.org", "tags": ["elite", "billionaires", "corporatocracy", "democracy", "plutocracy"], "description": "Opinion | To Save US Democracy, Tax the Rich at 90% | Common Dreams"}]