[{"page_rating_votes": 0, "page_rating": 0, "vote": 0, "permanent": false, "language": "en-US", "bookmarked": true, "source": "https://www.youtube.com/feeds/videos.xml?channel_id=UC-jwqP4zRycWJcy1aYDZMyw", "artist": null, "user": null, "page_rating_visits": 0, "dead": false, "date_published": "1985-12-15T08:29:11+00:00", "thumbnail": null, "tags": ["bezmenov", "neomarxism", "propaganda", "socialism", "all time"], "album": null, "comments": [], "title": "Yuri Bezmenov on the Useful Idiots (AKA the left)", "page_rating_contents": 0, "age": 0, "description": "Yuri Bezmenov on the Useful Idiots (AKA the left)", "link": "https://www.youtube.com/watch?v=EFW_i9NtP4I"}, {"page_rating_votes": 0, "page_rating": 0, "vote": 0, "permanent": false, "language": "en-US", "bookmarked": true, "source": "https://www.youtube.com/feeds/videos.xml?channel_id=UC_S8ZlDCRkMMgc7ciw8X-hg", "artist": null, "user": null, "page_rating_visits": 0, "dead": false, "date_published": "1985-11-06T20:58:26+00:00", "thumbnail": null, "tags": ["propaganda", "neomarxism", "socialism", "bezmenov"], "album": null, "comments": [], "title": "KGB Defector Yuri Bezmenov 1985 Interview. Explains KGB Manipulation of US Public Opinion", "page_rating_contents": 0, "age": 0, "description": "KGB Defector Yuri Bezmenov 1985 Interview. Explains KGB Manipulation of US Public Opinion", "link": "https://www.youtube.com/watch?v=pOmXiapfCs8"}, {"page_rating_votes": 0, "page_rating": 0, "vote": 0, "permanent": false, "language": "en", "bookmarked": true, "source": "https://en.wikipedia.org", "artist": "https://en.wikipedia.org", "user": "rumpel", "page_rating_visits": 4, "dead": false, "date_published": "1985-07-10T12:05:12+00:00", "thumbnail": null, "tags": ["france", "greenpeace", "government"], "album": "https://en.wikipedia.org", "comments": [], "title": "Sinking of the Rainbow Warrior - Wikipedia", "page_rating_contents": 0, "age": null, "description": "Sinking of the Rainbow Warrior - Wikipedia", "link": "https://en.wikipedia.org/wiki/Sinking_of_the_Rainbow_Warrior"}]