[{"source": "http://feeds.arstechnica.com/arstechnica/index/", "link": "https://arstechnica.com/?p=1902850", "title": "Myth, busted: Apatosaurus didn\u2019t produce sonic booms when whipping its tail", "date_published": "2022-12-08 19:54:04+00:00", "description": "Former Microsoft CTO Nathan Myhrvold did first computer simulations in late 1990s.", "persistent": false}, {"source": "http://feeds.arstechnica.com/arstechnica/index/", "link": "https://arstechnica.com/?p=1903011", "title": "FTC files suit to stop Microsoft\u2019s $69 billion Activision purchase", "date_published": "2022-12-08 19:39:38+00:00", "description": "Microsoft would gain \"means and motive to harm competition,\" regulator says.", "persistent": false}, {"source": "http://feeds.arstechnica.com/arstechnica/index/", "link": "https://arstechnica.com/?p=1902931", "title": "A quick look at AMD\u2019s Radeon RX 7900 XTX, which is smaller than an RTX 4080", "date_published": "2022-12-08 19:18:48+00:00", "description": "We can't talk about performance yet, but these GPUs should fit in most PC cases.", "persistent": false}, {"source": "http://feeds.arstechnica.com/arstechnica/index/", "link": "https://arstechnica.com/?p=1902914", "title": "Google\u2019s cost-cutters come for Waze, will lose status as independent company", "date_published": "2022-12-08 18:59:58+00:00", "description": "Google says it \"remains deeply committed\" to the Waze app.", "persistent": false}, {"source": "http://feeds.arstechnica.com/arstechnica/index/", "link": "https://arstechnica.com/?p=1902915", "title": "North Korean hackers once again exploit Internet Explorer\u2019s leftover bits", "date_published": "2022-12-08 18:43:57+00:00", "description": "There are still lots of ways to exploit Internet Explorer through a Word doc.", "persistent": false}, {"source": "http://feeds.arstechnica.com/arstechnica/index/", "link": "https://arstechnica.com/?p=1902911", "title": "The clock is rapidly ticking on Apple\u2019s Lightning charger", "date_published": "2022-12-08 18:36:06+00:00", "description": "EU government says USB-C compliance is mandatory by December 28, 2024.", "persistent": false}, {"source": "http://feeds.arstechnica.com/arstechnica/index/", "link": "https://arstechnica.com/?p=1902891", "title": "Twitter Blue will reportedly cost $11 in App Store so Musk can avoid Apple fees", "date_published": "2022-12-08 15:20:51+00:00", "description": "Reports suggest Musk is looking to pass Apple fees on to Twitter users.", "persistent": false}, {"source": "http://feeds.arstechnica.com/arstechnica/index/", "link": "https://arstechnica.com/?p=1902880", "title": "General Motors installs the first of 40,000 new EV chargers", "date_published": "2022-12-08 13:42:44+00:00", "description": "Nearly 1,000 GM dealers have enrolled in the program to double level 2 chargers.", "persistent": false}, {"source": "http://feeds.arstechnica.com/arstechnica/index/", "link": "https://arstechnica.com/?p=1902276", "title": "Win hardware, collectibles, and more in the 2022 Ars Technica Charity Drive", "date_published": "2022-12-08 12:30:51+00:00", "description": "Help yourself to prizes by helping us raise money for good causes.", "persistent": false}, {"source": "http://feeds.arstechnica.com/arstechnica/index/", "link": "https://arstechnica.com/?p=1902831", "title": "Amazon\u2019s Echo Show 15 smart display becomes a portable Fire TV", "date_published": "2022-12-08 00:09:27+00:00", "description": "Amazon already had a lot of success with Fire TV devices.", "persistent": false}]