[{"url": "https://tvn24.pl/wiadomosci-ze-swiata,2.xml", "link": "https://tvn24.pl/tvnwarszawa/komunikacja/warszawa-linie-cmentarne-2022-jak-dojechac-na-brodno-powazki-wolke-i-inne-cmentarze-rozklad-22-28-pazdziernika-6172556?source=rss", "title": "Pierwsze zmiany w komunikacji przed 1 listopada. Ruszaj\u0105 linie cmentarne", "date_published": "2022-10-21 05:02:11+00:00", "description": "<img alt=\"Pierwsze zmiany w komunikacji przed 1 listopada. Ruszaj\u0105 linie cmentarne\" src=\"https://tvn24.pl/tvnwarszawa/najnowsze/cdn-zdjecie-dj74pj-linie-cmentarne-beda-kursowaly-od-soboty-22-pazdziernika-6172559/alternates/LANDSCAPE_1280\" />\n    Trzy linie cmentarne rozpoczynaj\u0105 kursowanie ju\u017c w nadchodz\u0105cy weekend. Od soboty b\u0119dzie mo\u017cna dotrze\u0107 nimi na cmentarze P\u00f3\u0142nocny, Pow\u0105zkowski i Br\u00f3dnowski. Zarz\u0105d Transportu Miejskiego wprowadzi te\u017c zmiany w rozk\u0142adach jazdy linii podstawowych, kt\u00f3re pr"}]