[{"url": "https://www.androidauthority.com/feed/", "link": "https://www.androidauthority.com/google-pixel-watch-3042018/", "title": "Google Pixel Watch: Everything we know so far (Updated: September 6)", "date_published": "2022-09-06 19:00:35+00:00", "description": "Update: The Pixel Watch may be the first smartwatch packing Google Fi support."}, {"url": "https://www.androidauthority.com/feed/", "link": "https://www.androidauthority.com/watch-5-pro-charging-cradle-3205663/", "title": "New charging cradle is Samsung\u2019s answer to the Watch 5 Pro\u2019s design flaw", "date_published": "2022-09-06 18:39:18+00:00", "description": "Samsung listed a new charging cradle for the Galaxy Watch 5 Pro, but doesn't give a price or release date."}, {"url": "https://www.androidauthority.com/feed/", "link": "https://www.androidauthority.com/best-phone-deals-2-1111885/", "title": "Pay just $399 for the OnePlus 9, and more of the best phone deals", "date_published": "2022-09-06 18:35:04+00:00", "description": "This promo code knocks $200 off the asking price of the still-excellent OnePlus 9."}, {"url": "https://www.androidauthority.com/feed/", "link": "https://www.androidauthority.com/september-2022-android-security-patch-3205703/", "title": "September 2022 Android security patch here for Pixels, but not Pixel 6a yet", "date_published": "2022-09-06 18:14:28+00:00", "description": "There's also a fix that brings \"additional improvements for fingerprint recognition and response.\""}, {"url": "https://www.androidauthority.com/feed/", "link": "https://www.androidauthority.com/google-tensor-g2-3205707/", "title": "Google finally gets around to naming the second-gen Tensor chip", "date_published": "2022-09-06 17:58:00+00:00", "description": "Apparently, Google didn't think \"Tensor 2\" was good enough."}, {"url": "https://www.androidauthority.com/feed/", "link": "https://www.androidauthority.com/how-to-reset-ps5-controller-3204531/", "title": "How to reset a PS5 controller", "date_published": "2022-09-06 17:44:23+00:00", "description": "If your DualSense just won't sync, try resetting it."}, {"url": "https://www.androidauthority.com/feed/", "link": "https://www.androidauthority.com/google-pixel-7-launch-3205657/", "title": "Here is the confirmed Pixel 7 launch date and other info", "date_published": "2022-09-06 16:38:50+00:00", "description": "This will be an in-person show for the first time in years."}, {"url": "https://www.androidauthority.com/feed/", "link": "https://www.androidauthority.com/google-samsung-android-12l-3205615/", "title": "Google only agreed to work on Android 12L if Samsung made a foldable every year", "date_published": "2022-09-06 16:30:17+00:00", "description": "Google wanted Samsung to prove its commitment by following through on one big request."}, {"url": "https://www.androidauthority.com/feed/", "link": "https://www.androidauthority.com/google-pixel-6a-vs-iphone-se-2022-camera-comparison-3198373/", "title": "Google Pixel 6a vs iPhone SE (2022) camera shootout: Affordable excellence", "date_published": "2022-09-06 16:00:32+00:00", "description": "Two completely different approaches to photography, only one winner."}, {"url": "https://www.androidauthority.com/feed/", "link": "https://www.androidauthority.com/curved-displays-smartphone-poll-results-3205537/", "title": "You told us: Most of you don\u2019t care for curved displays, to put it mildly", "date_published": "2022-09-06 16:00:26+00:00", "description": "Only one in five polled readers said they actually liked curved screens on their smartphones."}, {"url": "https://www.androidauthority.com/feed/", "link": "https://www.androidauthority.com/iphone-13-sales-banned-brazil-3205624/", "title": "Country bans iPhone sales due to there not being a charger included", "date_published": "2022-09-06 15:30:57+00:00", "description": "Apple would also get slapped with a daily fine if it tries to circumvent the ban."}, {"url": "https://www.androidauthority.com/feed/", "link": "https://www.androidauthority.com/snapdragon-4-gen-1-snapdragon-6-gen-1-3205443/", "title": "Snapdragon 4 Gen 1, 6 Gen 1 announced: Premium features trickle down", "date_published": "2022-09-06 15:00:25+00:00", "description": "The Snapdragon 4 Gen 1 seems like a Snapdragon 695 Plus, if anything."}, {"url": "https://www.androidauthority.com/feed/", "link": "https://www.androidauthority.com/best-android-emulators-for-pc-655308/", "title": "15 best Android emulators for PC and Mac of 2022", "date_published": "2022-09-06 14:30:13+00:00", "description": "Play games, do productive things, and run Android apps and games right from your computer."}, {"url": "https://www.androidauthority.com/feed/", "link": "https://www.androidauthority.com/eve-matter-smart-home-3205171/", "title": "A Google speaker controlling Apple Homekit accessories? We just saw it in action", "date_published": "2022-09-06 14:20:17+00:00", "description": "The Matter smart home protocol is almost ready and we got to see its benefits in a simple demo."}, {"url": "https://www.androidauthority.com/feed/", "link": "https://www.androidauthority.com/best-cheap-samsung-galaxy-tab-deals-1119065/", "title": "Save $160 on the Galaxy Tab S8 Plus, and more Samsung Galaxy Tab deals", "date_published": "2022-09-06 13:40:35+00:00", "description": "Several of the best Samsung slates are on offer right now, including the best price to date on the flagship tablet."}, {"url": "https://www.androidauthority.com/feed/", "link": "https://www.androidauthority.com/huawei-mate-50-3205547/", "title": "Huawei Mate 50 series beats rivals to the punch with satellite support", "date_published": "2022-09-06 12:44:14+00:00", "description": "Huawei's new flagships also offer a primary camera capable of switching from f/1.4 aperture all the way to f/4."}, {"url": "https://www.androidauthority.com/feed/", "link": "https://www.androidauthority.com/daily-authority-september-6-2022-3205293/", "title": "Daily Authority: \ud83c\udfa7 Headphones smarten up", "date_published": "2022-09-06 10:16:33+00:00", "description": "Smarter headphones, Apple Watch Pro leaks, Rick and Morty's God of War: Ragnarok trailer, and more in today's top tech news."}, {"url": "https://www.androidauthority.com/feed/", "link": "https://www.androidauthority.com/samsung-galaxy-z-fold-3-updates-3032543/", "title": "Samsung Galaxy Z Fold 3 starts receiving the Android 12L update", "date_published": "2022-09-06 07:36:15+00:00", "description": "UPDATE: The Galaxy Z Fold 3 is getting a number of new features with One UI 4.1.1 based on Android 12L."}, {"url": "https://www.androidauthority.com/feed/", "link": "https://www.androidauthority.com/fitbit-irregular-heart-rate-afib-markets-3204204/", "title": "Fitbit brings irregular heart rhythm notifications to over 20 new countries", "date_published": "2022-09-06 06:52:09+00:00", "description": "Irregular heart rate detection is now available in over a dozen European countries, Hong Kong, and Canada."}, {"url": "https://www.androidauthority.com/feed/", "link": "https://www.androidauthority.com/apple-watch-pro-new-button-3205440/", "title": "Apple Watch Pro leaks with mysterious new button", "date_published": "2022-09-06 05:30:15+00:00", "description": "The largest Apple Watch ever with a programmable button."}]